{
  "post_url": "https://www.cvbankas.lt/data-analyst-vilniuje/1-9460784",
  "img_url": "https://cvbankas-img.dgn.lt/companylogo_2_18273607/emporionas.jpg",
  "position": "Data Analyst",
  "company": "UAB \u201eOvoko\u201c",
  "salary": "2500-5000",
  "city": "Vilniuje",
  "date": "prie\u0161 16 d."
}{
  "post_url": "https://www.cvbankas.lt/data-analyst-vilniuje/1-9460784",
  "img_url": "https://cvbankas-img.dgn.lt/companylogo_2_18273607/emporionas.jpg",
  "position": "Data Analyst",
  "company": "UAB \u201eOvoko\u201c",
  "salary": "2500-5000",
  "city": "Vilniuje",
  "date": "prie\u0161 17 d."
}{
  "post_id": "9460784",
  "post_url": "https://www.cvbankas.lt/data-analyst-vilniuje/1-9460784",
  "img_url": "https://cvbankas-img.dgn.lt/companylogo_2_18273607/emporionas.jpg",
  "position": "Data Analyst",
  "company": "UAB \u201eOvoko\u201c",
  "salary": "2500-5000",
  "city": "Vilniuje",
  "time_passed": "prie\u0161 17 d.",
  "upload_time": "Thu Nov  3 21:34:03 2022"
}